{
  "validFluencies" : {
    "fluent" : true,
    "not fluent" : true
  },
  "validPOS" : {
    "adjective" : true,
    "adverb" : true,
    "greeting" : true,
    "noun" : true,
    "pronoun" : true,
    "question particle" : true,
    "question pronoun" : true,
    "time word" : true,
    "verb" : true
  },
  "vocab" : {
    "-MbmbVF_q4rJiYFduQ0j" : {
      "english" : [ "you" ],
      "fluency" : "notFluent",
      "notes" : "helpfulwalnut",
      "partsOfSpeech" : [ "pronoun", "noun" ],
      "pinyin" : "nǐ",
      "simplified" : "你",
      "traditional" : "你"
    }
  }
}